climatetimer/__init__.py
climatetimer/climatetimer.py
climatetimer/constants.py
climatetimer-0.3.2.dist-info/METADATA
climatetimer-0.3.2.dist-info/WHEEL
climatetimer-0.3.2.dist-info/licenses/LICENSE
climatetimer-0.3.2.dist-info/RECORD
