Metadata-Version: 2.4
Name: climatetimer
Version: 0.3.2
Summary: Compute time block IDs since major climate agreements.
Project-URL: Homepage, https://github.com/cameraink/climatetimer
Project-URL: Repository, https://github.com/cameraink/climatetimer
Author: Guillaume Dion
License-Expression: MIT
License-File: LICENSE
Keywords: Climate,Kyoto Agreement,Paris Agreement,Time Blocks,Timer
Classifier: Development Status :: 4 - Beta
Classifier: Intended Audience :: Developers
Classifier: Programming Language :: Python :: 3
Classifier: Programming Language :: Python :: 3.10
Classifier: Programming Language :: Python :: 3.11
Classifier: Programming Language :: Python :: 3.12
Classifier: Programming Language :: Python :: 3.13
Requires-Python: >=3.10
